{
    "name": "DMZ 평화공원",
    "desc": "DMZ(비무장지대) 세계평화공원 조성 기대감에 관련주로 언급되는 종목군. <본 섹터는 심리적 요인이 크게 작용하므로 종목별로는 실제 영위하는 사업내용과 섹터내용의 상관관계나 매출비중이 다소 낮을 수 있음.>",
    "child": [
        {
            "name": "서희건설",
            "desc": "DMZ 세계평화공원 조성 기대감에 한국지뢰제거연구소와 업무 협약을 체결하고, 국내외 지뢰제거 사업 참여 예정 사실이 부각.",
            "code": "035890",
            "market": "KOSPI"
        },
        {
            "name": "시그네틱스",
            "desc": "DMZ 세계평화공원 조성 기대감에 경기 파주에 제2공장 증축 관련 사실이 시장에서 부각.",
            "code": "033170",
            "market": "KOSPI"
        },
        {
            "name": "용평리조트",
            "desc": "최대주주 세계기독교통일신령협회유지재단이 경기도 파주에 대규모 토지를 보유하고 있는 점이 시장에서 부각",
            "code": "070960",
            "market": "KOSDAQ"
        },
        {
            "name": "모헨즈",
            "desc": "DMZ 세계평화공원 조성 기대감에 강원도 토종(강원도 춘천) 레미콘 업체 덕원산업 지분 보유 사실이 부각.",
            "code": "006920",
            "market": "KOSPI"
        },
        {
            "name": "자연과환경",
            "desc": "환경생태복원(하천재정비 및 자연형 하천조성사업 등) 분야 관련 사업 영위. DMZ 세계평화공원 조성 기대감.",
            "code": "043910",
            "market": "KOSPI"
        },
        {
            "name": "누리플랜",
            "desc": "DMZ 세계평화공원 조성 기대감에 공원 경관 조명 사업을 영위하고 있는 사실이 부각.",
            "code": "069140",
            "market": "KOSPI"
        },
        {
            "name": "이화공영",
            "desc": "DMZ 세계평화공원 조성 기대감에 경기도 파주에 창고부지 소유.",
            "code": "001840",
            "market": "KOSPI"
        },
        {
            "name": "퍼스텍",
            "desc": "후성그룹 계열의 방위산업 전문업체. 항공우주(헬기 및 전투기), 유도무기(미사일), 지상무기(기동 및 화포), 해상수중무기(함포), 자동소화장치, 무인화(휴대용 소형로봇) 등 다양한 분야의 방위사업을 영위. 국방연구원 등과 함께 지뢰제거 로봇 개발을 진행중.",
            "code": "010820",
            "market": "KOSDAQ"
        },
        {
            "name": "시공테크",
            "desc": "DMZ 세계평화공원 조성 기대감에 각종 생태공원 설치 경험과 지난 2009년 DMZ 평화생명동산 전시물 제작설치 사업 입찰에 참여한 점이 시장에서 부각.",
            "code": "020710",
            "market": "KOSPI"
        },
        {
            "name": "유진로봇",
            "desc": "DMZ 세계평화공원 조성 기대감에 비무장지대(DMZ)에서 군사 임무를 수행할 수 있는 로봇과 재난 지역에서 활동할 수 있는 로봇을 보유하고 있는 점이 부각.",
            "code": "056080",
            "market": "KOSPI"
        },
        {
            "name": "웰크론",
            "desc": "DMZ 세계평화공원 조성 기대감 속 지뢰 제거용 EOD방호복 생산 사실 부각.",
            "code": "065950",
            "market": "KOSPI"
        },
        {
            "name": "일신석재",
            "desc": "경기도 포천에 건물 및 토지를 보유하고 있는 점과 최대주주 세계기독교통일신령협회유지재단이 경기도 파주에 대규모 토지를 보유하고 있는 점이 시장에서 부각.",
            "code": "007110",
            "market": "KOSDAQ"
        },
        {
            "name": "코리아에스이",
            "desc": "DMZ 세계평화공원 조성 기대감에 영구앵커(토목공사시 안전 확보 등을 위해 사용되는 자재) 분야 관련 사업이 부각.",
            "code": "101670",
            "market": "KOSPI"
        },
        {
            "name": "웹스",
            "desc": "DMZ 세계평화공원 조성 기대감에 비무장지대(DMZ) 부근 환경정화 사업 수주 경험이 있다는 점이 부각.",
            "code": "196700",
            "market": "KOSPI"
        },
        {
            "name": "씨아이테크",
            "desc": "DMZ 세계평화공원 조성 기대감에 경기도 연천군 일대 토지 보유 사실이 시장에서 부각.",
            "code": "004920",
            "market": "KOSDAQ"
        },
        {
            "name": "크라운해태홀딩스",
            "desc": "비상장 계열사 해성농림이 접경지역인 파주 인근 양주에 100만평 부지를 보유하고 있는 사실이 시장에서 부각.",
            "code": "005740",
            "market": "KOSDAQ"
        },
        {
            "name": "딜리",
            "desc": "DMZ 세계평화공원 조성 기대감에 경기도 포천 토지 및 공장 소유.",
            "code": "131180",
            "market": "KOSPI"
        },
        {
            "name": "대창스틸",
            "desc": "DMZ 세계평화공원 조성 기대감에 경기도 파주에 공장 소유 사실이 부각.",
            "code": "140520",
            "market": "KOSPI"
        },
        {
            "name": "코아스",
            "desc": "DMZ 세계평화공원 조성 기대감에 경기도 파주 부동산 보유 사실이 부각.",
            "code": "071950",
            "market": "KOSDAQ"
        },
        {
            "name": "삼륭물산",
            "desc": "DMZ 세계평화공원 조성 기대감에 경기도 파주 공장 부지 및 공장 소유 사실이 부각.",
            "code": "014970",
            "market": "KOSPI"
        }
    ]
}